interval_timer/__init__.py
interval_timer/interval.py
interval_timer/interval_timer.py
interval_timer-1.0.0.dist-info/LICENSE
interval_timer-1.0.0.dist-info/WHEEL
interval_timer-1.0.0.dist-info/METADATA
interval_timer-1.0.0.dist-info/RECORD
