Metadata-Version: 2.1
Name: interval-timer
Version: 1.0.0
Summary: interval-timer is a Python package that enables iterating over a sequence of regular time intervals with high precision.
Home-page: https://github.com/morefigs/interval-timer
Author: morefigs
Requires-Python: >=3.10,<4.0
Classifier: Programming Language :: Python :: 3
Classifier: Programming Language :: Python :: 3.10
Classifier: Programming Language :: Python :: 3.11
